CONTRIBUTORS.txt
HISTORY.TXT
README.txt
bootstrap.py
buildout.cfg
setup.cfg
setup.py
src/archetypes/__init__.py
src/archetypes.schematuning.egg-info/PKG-INFO
src/archetypes.schematuning.egg-info/SOURCES.txt
src/archetypes.schematuning.egg-info/dependency_links.txt
src/archetypes.schematuning.egg-info/entry_points.txt
src/archetypes.schematuning.egg-info/namespace_packages.txt
src/archetypes.schematuning.egg-info/not-zip-safe
src/archetypes.schematuning.egg-info/requires.txt
src/archetypes.schematuning.egg-info/top_level.txt
src/archetypes/schematuning/__init__.py
src/archetypes/schematuning/configure.zcml
src/archetypes/schematuning/patch.py
src/archetypes/schematuning/at_tests/README.txt
src/archetypes/schematuning/at_tests/test_fields.py
src/archetypes/schematuning/at_tests/test_storage.py
src/archetypes/schematuning/at_tests/test_update_schema.py
src/archetypes/schematuning/tests/README.txt
src/archetypes/schematuning/tests/__init__.py
src/archetypes/schematuning/tests/base.py
src/archetypes/schematuning/tests/test_fields.py
src/archetypes/schematuning/tests/test_patch.py
src/archetypes/schematuning/tests/test_schemaextenders.py
src/archetypes/schematuning/tests/test_storage.py
src/archetypes/schematuning/tests/test_update_schema.py