Metadata-Version: 1.0
Name: archetypes.schematuning
Version: 1.2
Summary: More Speed with cached Archetypes Schemas.
Home-page: http://bluedynamics.com
Author: Jens Klein, Hedley Roos
Author-email: jens@bluedynamics.com
License: GPL
Platform: UNKNOWN
Classifier: Development Status :: 5 - Production/Stable
Classifier: Environment :: Web Environment
Classifier: Framework :: Plone
Classifier: Framework :: Zope2
Classifier: Intended Audience :: Developers
Classifier: License :: OSI Approved :: GNU General Public License (GPL)
Classifier: Operating System :: OS Independent
Classifier: Programming Language :: Python :: 2
Classifier: Topic :: Internet :: WWW/HTTP :: Dynamic Content
